fairdetect_dialga/__init__.py
fairdetect_dialga-0.2.dist-info/METADATA
fairdetect_dialga-0.2.dist-info/WHEEL
fairdetect_dialga-0.2.dist-info/top_level.txt
fairdetect_dialga-0.2.dist-info/RECORD
