Metadata-Version: 2.1
Name: fairdetect-dialga
Version: 0.2
Summary: Python Package to detect bias in datasets
Home-page: https://github.com/aousalmegrin/fairdetect_D
Author: Group D members
Author-email: aous.almegrin@student.ie.edu
License: MIT
Platform: UNKNOWN
